[
    {
        "university": "Acharya Nagarjuna University, Guntur (Id: U-0003)",
        "college": "Aazad College of Education (Id: C-39230)",
        "college_type": "Affiliated College",
        "state": "Andhra Pradesh",
        "district": "Prakasam"
    },
    {
        "university": "Acharya Nagarjuna University, Guntur (Id: U-0003)",
        "college": "Abhinav Institute of Management & Technology (Id: C-39450)",
        "college_type": "Affiliated College",
        "state": "Andhra Pradesh",
        "district": "Prakasam"
    },
    {
        "university": "Acharya Nagarjuna University, Guntur (Id: U-0003)",
        "college": "Abhyudaya Mahila Degree College (Id: C-32630)",
        "college_type": "Affiliated College",
        "state": "Andhra Pradesh",
        "district": "Guntur"
    },
    {
        "university": "Acharya Nagarjuna University, Guntur (Id: U-0003)",
        "college": "A.B.M. College (Id: C-32735)",
        "college_type": "Affiliated College",
        "state": "Andhra Pradesh",
        "district": "Prakasam"
    },
    {
        "university": "Acharya Nagarjuna University, Guntur (Id: U-0003)",
        "college": "A.B.R College of Education (Id: C-39231)",
        "college_type": "Affiliated College",
        "state": "Andhra Pradesh",
        "district": "Prakasam"
    },
    {
        "university": "Acharya Nagarjuna University, Guntur (Id: U-0003)",
        "college": "A.C.College (Day) (Id: C-32762)",
        "college_type": "Affiliated College",
        "state": "Andhra Pradesh",
        "district": "Guntur"
    },
    {
        "university": "Acharya Nagarjuna University, Guntur (Id: U-0003)",
        "college": "A.C.College of Law (Id: C-32792)",
        "college_type": "Affiliated College",
        "state": "Andhra Pradesh",
        "district": "Guntur"
    },
    {
        "university": "Acharya Nagarjuna University, Guntur (Id: U-0003)",
        "college": "A.C.Evening College (Id: C-32720)",
        "college_type": "Affiliated College",
        "state": "Andhra Pradesh",
        "district": "Guntur"
    },
    {
        "university": "Acharya Nagarjuna University, Guntur (Id: U-0003)",
        "college": "Acharya N.G.Ranga College of Education (Id: C-32793)",
        "college_type": "Affiliated College",
        "state": "Andhra Pradesh",
        "district": "Guntur"
    },
    {
        "university": "Acharya Nagarjuna University, Guntur (Id: U-0003)",
        "college": "Adarsa College of Education (Id: C-32801)",
        "college_type": "Affiliated College",
        "state": "Andhra Pradesh",
        "district": "Prakasam"
    },
    {
        "university": "Acharya Nagarjuna University, Guntur (Id: U-0003)",
        "college": "Adarsa Degree College for Women (Id: C-32733)",
        "college_type": "Affiliated College",
        "state": "Andhra Pradesh",
        "district": "Guntur"
    },
    {
        "university": "Acharya Nagarjuna University, Guntur (Id: U-0003)",
        "college": "A.G.K.M.College (Id: C-32664)",
        "college_type": "Affiliated College",
        "state": "Andhra Pradesh",
        "district": "Guntur"
    },
    {
        "university": "Acharya Nagarjuna University, Guntur (Id: U-0003)",
        "college": "A.L.College of Education (Id: C-32711)",
        "college_type": "Affiliated College",
        "state": "Andhra Pradesh",
        "district": "Guntur"
    },
    {
        "university": "Acharya Nagarjuna University, Guntur (Id: U-0003)",
        "college": "Ali College of Education (Id: C-39243)",
        "college_type": "Affiliated College",
        "state": "Andhra Pradesh",
        "district": "Guntur"
    },
    {
        "university": "Acharya Nagarjuna University, Guntur (Id: U-0003)",
        "college": "AL Momin College of Education (Id: C-39261)",
        "college_type": "Affiliated College",
        "state": "Andhra Pradesh",
        "district": "Prakasam"
    },
    {
        "university": "Acharya Nagarjuna University, Guntur (Id: U-0003)",
        "college": "Alpha College of Education (Id: C-39238)",
        "college_type": "Affiliated College",
        "state": "Andhra Pradesh",
        "district": "Prakasam"
    },
    {
        "university": "Acharya Nagarjuna University, Guntur (Id: U-0003)",
        "college": "Alpha College of Education, Kanigiri (Id: C-44489)",
        "college_type": "Affiliated College",
        "state": "Andhra Pradesh",
        "district": "Prakasam"
    },
    {
        "university": "Acharya Nagarjuna University, Guntur (Id: U-0003)",
        "college": "Alpha Degree College (Id: C-32797)",
        "college_type": "Affiliated College",
        "state": "Andhra Pradesh",
        "district": "Prakasam"
    },
    {
        "university": "Acharya Nagarjuna University, Guntur (Id: U-0003)",
        "college": "Aman Showkath B.Ed College (Id: C-39227)",
        "college_type": "Affiliated College",
        "state": "Andhra Pradesh",
        "district": "Guntur"
    },
    {
        "university": "Acharya Nagarjuna University, Guntur (Id: U-0003)",
        "college": "A.M.G.College of Education (Id: C-32649)",
        "college_type": "Affiliated College",
        "state": "Andhra Pradesh",
        "district": "Guntur"
    },
    {
        "university": "Acharya Nagarjuna University, Guntur (Id: U-0003)",
        "college": "A.M.G.Degree College for Women (Id: C-32769)",
        "college_type": "Affiliated College",
        "state": "Andhra Pradesh",
        "district": "Guntur"
    },
    {
        "university": "Acharya Nagarjuna University, Guntur (Id: U-0003)",
        "college": "A.M Reddy College of Education (Id: C-37211)",
        "college_type": "Affiliated College",
        "state": "Andhra Pradesh",
        "district": "Guntur"
    },
    {
        "university": "Acharya Nagarjuna University, Guntur (Id: U-0003)",
        "college": "A.M. Reddy Memorial College of Pharmacy (Id: C-39491)",
        "college_type": "Affiliated College",
        "state": "Andhra Pradesh",
        "district": "Guntur"
    },
    {
        "university": "Acharya Nagarjuna University, Guntur (Id: U-0003)",
        "college": "Amrutha College of Education (Id: C-39232)",
        "college_type": "Affiliated College",
        "state": "Andhra Pradesh",
        "district": "Prakasam"
    },
    {
        "university": "Acharya Nagarjuna University, Guntur (Id: U-0003)",
        "college": "Amrutha Degree College (Id: C-44105)",
        "college_type": "Affiliated College",
        "state": "Andhra Pradesh",
        "district": "Prakasam"
    },
    {
        "university": "Acharya Nagarjuna University, Guntur (Id: U-0003)",
        "college": "Andhra Kesari College of Education (Id: C-39275)",
        "college_type": "Affiliated College",
        "state": "Andhra Pradesh",
        "district": "Prakasam"
    },
    {
        "university": "Acharya Nagarjuna University, Guntur (Id: U-0003)",
        "college": "Andhra Kesari Vidya Kendram Degree College (Id: C-32631)",
        "college_type": "Affiliated College",
        "state": "Andhra Pradesh",
        "district": "Prakasam"
    },
    {
        "university": "Acharya Nagarjuna University, Guntur (Id: U-0003)",
        "college": "Andhra Muslim College (Id: C-32727)",
        "college_type": "Affiliated College",
        "state": "Andhra Pradesh",
        "district": "Guntur"
    },
    {
        "university": "Acharya Nagarjuna University, Guntur (Id: U-0003)",
        "college": "Andhra Muslim College of Education (Id: C-36923)",
        "college_type": "Affiliated College",
        "state": "Andhra Pradesh",
        "district": "Guntur"
    },
    {
        "university": "Acharya Nagarjuna University, Guntur (Id: U-0003)",
        "college": "Anitha Venkateswara College of Eduation (Id: C-39241)",
        "college_type": "Affiliated College",
        "state": "Andhra Pradesh",
        "district": "Guntur"
    },
    {
        "university": "Acharya Nagarjuna University, Guntur (Id: U-0003)",
        "college": "Annabattuni Satyanarayana Degree College (Id: C-32656)",
        "college_type": "Affiliated College",
        "state": "Andhra Pradesh",
        "district": "Guntur"
    },
    {
        "university": "Acharya Nagarjuna University, Guntur (Id: U-0003)",
        "college": "Anniebesant College of Education (Id: C-32740)",
        "college_type": "Affiliated College",
        "state": "Andhra Pradesh",
        "district": "Prakasam"
    },
    {
        "university": "Acharya Nagarjuna University, Guntur (Id: U-0003)",
        "college": "ANU PG Campus Ongole (Id: C-32629)",
        "college_type": "PG Center / Off-Campus Center",
        "state": "Andhra Pradesh",
        "district": "Prakasam"
    },
    {
        "university": "Acharya Nagarjuna University, Guntur (Id: U-0003)",
        "college": "A.P.Residential Degree College (Id: C-32778)",
        "college_type": "Affiliated College",
        "state": "Andhra Pradesh",
        "district": "Guntur"
    },
    {
        "university": "Acharya Nagarjuna University, Guntur (Id: U-0003)",
        "college": "Asha College of Education (Id: C-39244)",
        "college_type": "Affiliated College",
        "state": "Andhra Pradesh",
        "district": "Prakasam"
    },
    {
        "university": "Acharya Nagarjuna University, Guntur (Id: U-0003)",
        "college": "A.S.M & A.W. D Women's Degree College (Id: C-39265)",
        "college_type": "Affiliated College",
        "state": "Andhra Pradesh",
        "district": "Guntur"
    },
    {
        "university": "Acharya Nagarjuna University, Guntur (Id: U-0003)",
        "college": "A.S.N Pharmacy College, Tenali (Id: C-39489)",
        "college_type": "Affiliated College",
        "state": "Andhra Pradesh",
        "district": "Guntur"
    },
    {
        "university": "Acharya Nagarjuna University, Guntur (Id: U-0003)",
        "college": "B.A & K.R College of Education (Id: C-39269)",
        "college_type": "Affiliated College",
        "state": "Andhra Pradesh",
        "district": "Prakasam"
    },
    {
        "university": "Acharya Nagarjuna University, Guntur (Id: U-0003)",
        "college": "B.A & K.R Degree College (Id: C-32771)",
        "college_type": "Affiliated College",
        "state": "Andhra Pradesh",
        "district": "Prakasam"
    },
    {
        "university": "Acharya Nagarjuna University, Guntur (Id: U-0003)",
        "college": "Balaji Degree College (Id: C-32669)",
        "college_type": "Affiliated College",
        "state": "Andhra Pradesh",
        "district": "Guntur"
    },
    {
        "university": "Acharya Nagarjuna University, Guntur (Id: U-0003)",
        "college": "Bapatla College of Arts & Science (Id: C-32779)",
        "college_type": "Affiliated College",
        "state": "Andhra Pradesh",
        "district": "Guntur"
    },
    {
        "university": "Acharya Nagarjuna University, Guntur (Id: U-0003)",
        "college": "Bapatla Engineering College (Id: C-42660)",
        "college_type": "Affiliated College",
        "state": "Andhra Pradesh",
        "district": "Guntur"
    },
    {
        "university": "Acharya Nagarjuna University, Guntur (Id: U-0003)",
        "college": "Bapatla Womens Engineering College (Id: C-39453)",
        "college_type": "Affiliated College",
        "state": "Andhra Pradesh",
        "district": "Guntur"
    },
    {
        "university": "Acharya Nagarjuna University, Guntur (Id: U-0003)",
        "college": "Bapuji College of Education (Id: C-39240)",
        "college_type": "Affiliated College",
        "state": "Andhra Pradesh",
        "district": "Guntur"
    },
    {
        "university": "Acharya Nagarjuna University, Guntur (Id: U-0003)",
        "college": "B.B.H Degree College (Id: C-32756)",
        "college_type": "Affiliated College",
        "state": "Andhra Pradesh",
        "district": "Prakasam"
    },
    {
        "university": "Acharya Nagarjuna University, Guntur (Id: U-0003)",
        "college": "B.G Degree College, Sattenapalli (Id: C-40608)",
        "college_type": "Affiliated College",
        "state": "Andhra Pradesh",
        "district": "Guntur"
    },
    {
        "university": "Acharya Nagarjuna University, Guntur (Id: U-0003)",
        "college": "Bharathi Degree College (Id: C-32667)",
        "college_type": "Affiliated College",
        "state": "Andhra Pradesh",
        "district": "Prakasam"
    },
    {
        "university": "Acharya Nagarjuna University, Guntur (Id: U-0003)",
        "college": "Bhashyam College of Education (Id: C-39234)",
        "college_type": "Affiliated College",
        "state": "Andhra Pradesh",
        "district": "Guntur"
    },
    {
        "university": "Acharya Nagarjuna University, Guntur (Id: U-0003)",
        "college": "B.H.H Degree College for Women (Id: C-32803)",
        "college_type": "Affiliated College",
        "state": "Andhra Pradesh",
        "district": "Guntur"
    },
    {
        "university": "Acharya Nagarjuna University, Guntur (Id: U-0003)",
        "college": "B.M.Degree College, P.Dornala (Id: C-39300)",
        "college_type": "Affiliated College",
        "state": "Andhra Pradesh",
        "district": "Prakasam"
    },
    {
        "university": "Acharya Nagarjuna University, Guntur (Id: U-0003)",
        "college": "BMRM Jhansi B.Ed College (Id: C-39237)",
        "college_type": "Affiliated College",
        "state": "Andhra Pradesh",
        "district": "Prakasam"
    },
    {
        "university": "Acharya Nagarjuna University, Guntur (Id: U-0003)",
        "college": "B.R College of Education (Id: C-37221)",
        "college_type": "Affiliated College",
        "state": "Andhra Pradesh",
        "district": "Guntur"
    },
    {
        "university": "Acharya Nagarjuna University, Guntur (Id: U-0003)",
        "college": "B.S.S.B College (Id: C-32652)",
        "college_type": "Affiliated College",
        "state": "Andhra Pradesh",
        "district": "Guntur"
    },
    {
        "university": "Acharya Nagarjuna University, Guntur (Id: U-0003)",
        "college": "B.V.S.P.M Degree College (Id: C-32663)",
        "college_type": "Affiliated College",
        "state": "Andhra Pradesh",
        "district": "Prakasam"
    },
    {
        "university": "Acharya Nagarjuna University, Guntur (Id: U-0003)",
        "college": "Career Degree College (Id: C-32782)",
        "college_type": "Affiliated College",
        "state": "Andhra Pradesh",
        "district": "Guntur"
    },
    {
        "university": "Acharya Nagarjuna University, Guntur (Id: U-0003)",
        "college": "Chaitanya Bharathi Degree College, Chirala (Id: C-42659)",
        "college_type": "Affiliated College",
        "state": "Andhra Pradesh",
        "district": "Prakasam"
    },
    {
        "university": "Acharya Nagarjuna University, Guntur (Id: U-0003)",
        "college": "Chaitanya College of Education (Id: C-32763)",
        "college_type": "Affiliated College",
        "state": "Andhra Pradesh",
        "district": "Prakasam"
    },
    {
        "university": "Acharya Nagarjuna University, Guntur (Id: U-0003)",
        "college": "Chakradhar Degree College, Macherla (Id: C-39308)",
        "college_type": "Affiliated College",
        "state": "Andhra Pradesh",
        "district": "Guntur"
    },
    {
        "university": "Acharya Nagarjuna University, Guntur (Id: U-0003)",
        "college": "Chalapathi Degree College, Lam (Id: C-42706)",
        "college_type": "Affiliated College",
        "state": "Andhra Pradesh",
        "district": "Guntur"
    },
    {
        "university": "Acharya Nagarjuna University, Guntur (Id: U-0003)",
        "college": "Chalapathi Institute of Engineering & Technology, Lam (Id: C-39475)",
        "college_type": "Affiliated College",
        "state": "Andhra Pradesh",
        "district": "Guntur"
    },
    {
        "university": "Acharya Nagarjuna University, Guntur (Id: U-0003)",
        "college": "Chalapathi Institute of Pharmaceutical Sciences, Lam (Id: C-39486)",
        "college_type": "Affiliated College",
        "state": "Andhra Pradesh",
        "district": "Guntur"
    },
    {
        "university": "Acharya Nagarjuna University, Guntur (Id: U-0003)",
        "college": "Chebrolu Hanumaiah College of Pharmaceutical Sciences (Id: C-39452)",
        "college_type": "Affiliated College",
        "state": "Andhra Pradesh",
        "district": "Guntur"
    },
    {
        "university": "Acharya Nagarjuna University, Guntur (Id: U-0003)",
        "college": "Chegireddy Linga Reddy Instt of Management (Id: C-39466)",
        "college_type": "Affiliated College",
        "state": "Andhra Pradesh",
        "district": "Prakasam"
    },
    {
        "university": "Acharya Nagarjuna University, Guntur (Id: U-0003)",
        "college": "Chirala College of PG Studies, Chirala (Id: C-39457)",
        "college_type": "Affiliated College",
        "state": "Andhra Pradesh",
        "district": "Guntur"
    },
    {
        "university": "Acharya Nagarjuna University, Guntur (Id: U-0003)",
        "college": "Chiristian Women's College (Id: C-32703)",
        "college_type": "Affiliated College",
        "state": "Andhra Pradesh",
        "district": "Guntur"
    },
    {
        "university": "Acharya Nagarjuna University, Guntur (Id: U-0003)",
        "college": "Christu Jayanthi Jubilee College (P.G.) (Id: C-32819)",
        "college_type": "Affiliated College",
        "state": "Andhra Pradesh",
        "district": "Guntur"
    },
    {
        "university": "Acharya Nagarjuna University, Guntur (Id: U-0003)",
        "college": "C.I.L.For Rural Management (Id: C-42663)",
        "college_type": "Affiliated College",
        "state": "Andhra Pradesh",
        "district": "Guntur"
    },
    {
        "university": "Acharya Nagarjuna University, Guntur (Id: U-0003)",
        "college": "C.R. College (Id: C-32796)",
        "college_type": "Affiliated College",
        "state": "Andhra Pradesh",
        "district": "Guntur"
    },
    {
        "university": "Acharya Nagarjuna University, Guntur (Id: U-0003)",
        "college": "C.S.R. Sarma College (Id: C-32702)",
        "college_type": "Affiliated College",
        "state": "Andhra Pradesh",
        "district": "Prakasam"
    },
    {
        "university": "Acharya Nagarjuna University, Guntur (Id: U-0003)",
        "college": "D.C.R.M Degree College (Id: C-32662)",
        "college_type": "Affiliated College",
        "state": "Andhra Pradesh",
        "district": "Prakasam"
    },
    {
        "university": "Acharya Nagarjuna University, Guntur (Id: U-0003)",
        "college": "D.C.R.M P.G College, MBA (Id: C-32655)",
        "college_type": "Affiliated College",
        "state": "Andhra Pradesh",
        "district": "Prakasam"
    },
    {
        "university": "Acharya Nagarjuna University, Guntur (Id: U-0003)",
        "college": "Devathi Venkata Subbaiah Degree College (Id: C-32710)",
        "college_type": "Affiliated College",
        "state": "Andhra Pradesh",
        "district": "Prakasam"
    },
    {
        "university": "Acharya Nagarjuna University, Guntur (Id: U-0003)",
        "college": "Devathi Venkata Subbiah College of Education (Id: C-37223)",
        "college_type": "Affiliated College",
        "state": "Andhra Pradesh",
        "district": "Prakasam"
    },
    {
        "university": "Acharya Nagarjuna University, Guntur (Id: U-0003)",
        "college": "Don Bosco College (P.G.) (Id: C-32804)",
        "college_type": "Affiliated College",
        "state": "Andhra Pradesh",
        "district": "Guntur"
    },
    {
        "university": "Acharya Nagarjuna University, Guntur (Id: U-0003)",
        "college": "Dr. B.R.Ambedkar Centenary Degree College (Id: C-32741)",
        "college_type": "Affiliated College",
        "state": "Andhra Pradesh",
        "district": "Guntur"
    },
    {
        "university": "Acharya Nagarjuna University, Guntur (Id: U-0003)",
        "college": "Dr.Homi Jahangir Baba Degree College (Id: C-32813)",
        "college_type": "Affiliated College",
        "state": "Andhra Pradesh",
        "district": "Guntur"
    },
    {
        "university": "Acharya Nagarjuna University, Guntur (Id: U-0003)",
        "college": "Dr. Jayapradamba Degree College (Id: C-32776)",
        "college_type": "Affiliated College",
        "state": "Andhra Pradesh",
        "district": "Guntur"
    },
    {
        "university": "Acharya Nagarjuna University, Guntur (Id: U-0003)",
        "college": "Dr. K.R.R.M. Degree College (Id: C-32636)",
        "college_type": "Affiliated College",
        "state": "Andhra Pradesh",
        "district": "Guntur"
    },
    {
        "university": "Acharya Nagarjuna University, Guntur (Id: U-0003)",
        "college": "Dr. K.S.P.R College of Education (Id: C-39242)",
        "college_type": "Affiliated College",
        "state": "Andhra Pradesh",
        "district": "Guntur"
    },
    {
        "university": "Acharya Nagarjuna University, Guntur (Id: U-0003)",
        "college": "Dr.K.V.K. Sanskrit College (Id: C-32692)",
        "college_type": "Affiliated College",
        "state": "Andhra Pradesh",
        "district": "Guntur"
    },
    {
        "university": "Acharya Nagarjuna University, Guntur (Id: U-0003)",
        "college": "D.R.N.S.C.V.S. College (Id: C-32790)",
        "college_type": "Affiliated College",
        "state": "Andhra Pradesh",
        "district": "Guntur"
    },
    {
        "university": "Acharya Nagarjuna University, Guntur (Id: U-0003)",
        "college": "Dr. Samuel George College of Pharmaceutical Science (Id: C-32811)",
        "college_type": "Affiliated College",
        "state": "Andhra Pradesh",
        "district": "Prakasam"
    },
    {
        "university": "Acharya Nagarjuna University, Guntur (Id: U-0003)",
        "college": "Dr. Zakir Hussain College of Education (Id: C-36922)",
        "college_type": "Affiliated College",
        "state": "Andhra Pradesh",
        "district": "Guntur"
    },
    {
        "university": "Acharya Nagarjuna University, Guntur (Id: U-0003)",
        "college": "D.S.Govt. Degree College for Women, Ongole (Id: C-32817)",
        "college_type": "Affiliated College",
        "state": "Andhra Pradesh",
        "district": "Prakasam"
    },
    {
        "university": "Acharya Nagarjuna University, Guntur (Id: U-0003)",
        "college": "Erigineni Tirupati Naidu & Lakshmamma Degree College (Id: C-32786)",
        "college_type": "Affiliated College",
        "state": "Andhra Pradesh",
        "district": "Prakasam"
    },
    {
        "university": "Acharya Nagarjuna University, Guntur (Id: U-0003)",
        "college": "Fatima College of Education (Id: C-32654)",
        "college_type": "Affiliated College",
        "state": "Andhra Pradesh",
        "district": "Guntur"
    },
    {
        "university": "Acharya Nagarjuna University, Guntur (Id: U-0003)",
        "college": "G.C.K.V.N. Degree College (Id: C-32628)",
        "college_type": "Affiliated College",
        "state": "Andhra Pradesh",
        "district": "Guntur"
    },
    {
        "university": "Acharya Nagarjuna University, Guntur (Id: U-0003)",
        "college": "G.C & Y P N Degree College (Id: C-32698)",
        "college_type": "Affiliated College",
        "state": "Andhra Pradesh",
        "district": "Prakasam"
    },
    {
        "university": "Acharya Nagarjuna University, Guntur (Id: U-0003)",
        "college": "Geetham Degree College (Id: C-32777)",
        "college_type": "Affiliated College",
        "state": "Andhra Pradesh",
        "district": "Prakasam"
    },
    {
        "university": "Acharya Nagarjuna University, Guntur (Id: U-0003)",
        "college": "Geethanjali Degree College, Darsi (Id: C-41015)",
        "college_type": "Affiliated College",
        "state": "Andhra Pradesh",
        "district": "Prakasam"
    },
    {
        "university": "Acharya Nagarjuna University, Guntur (Id: U-0003)",
        "college": "Geethika B.Ed College (Id: C-39236)",
        "college_type": "Affiliated College",
        "state": "Andhra Pradesh",
        "district": "Guntur"
    },
    {
        "university": "Acharya Nagarjuna University, Guntur (Id: U-0003)",
        "college": "Goutham College of Education (Id: C-39310)",
        "college_type": "Affiliated College",
        "state": "Andhra Pradesh",
        "district": "Prakasam"
    },
    {
        "university": "Acharya Nagarjuna University, Guntur (Id: U-0003)",
        "college": "Government Degree College, Cumbum (Id: C-39309)",
        "college_type": "Affiliated College",
        "state": "Andhra Pradesh",
        "district": "Prakasam"
    },
    {
        "university": "Acharya Nagarjuna University, Guntur (Id: U-0003)",
        "college": "Government Degree College, Yerragondapalem (Id: C-39295)",
        "college_type": "Affiliated College",
        "state": "Andhra Pradesh",
        "district": "Prakasam"
    },
    {
        "university": "Acharya Nagarjuna University, Guntur (Id: U-0003)",
        "college": "Govt. Degree College, Chebrolu (Id: C-32624)",
        "college_type": "Affiliated College",
        "state": "Andhra Pradesh",
        "district": "Guntur"
    },
    {
        "university": "Acharya Nagarjuna University, Guntur (Id: U-0003)",
        "college": "Govt. Degree College for Women, Guntur (Id: C-32670)",
        "college_type": "Affiliated College",
        "state": "Andhra Pradesh",
        "district": "Guntur"
    },
    {
        "university": "Acharya Nagarjuna University, Guntur (Id: U-0003)",
        "college": "Govt. Degree College, Kanigiri (Id: C-32748)",
        "college_type": "Affiliated College",
        "state": "Andhra Pradesh",
        "district": "Prakasam"
    },
    {
        "university": "Acharya Nagarjuna University, Guntur (Id: U-0003)",
        "college": "G.R.K Degree College, Maddipadu (Id: C-39306)",
        "college_type": "Affiliated College",
        "state": "Andhra Pradesh",
        "district": "Prakasam"
    },
    {
        "university": "Acharya Nagarjuna University, Guntur (Id: U-0003)",
        "college": "G.R.R. & T.P.R. Degree College (Id: C-42707)",
        "college_type": "Affiliated College",
        "state": "Andhra Pradesh",
        "district": "Prakasam"
    },
    {
        "university": "Acharya Nagarjuna University, Guntur (Id: U-0003)",
        "college": "G.S.R. Degree College (Id: C-41014)",
        "college_type": "Affiliated College",
        "state": "Andhra Pradesh",
        "district": "Guntur"
    },
    {
        "university": "Acharya Nagarjuna University, Guntur (Id: U-0003)",
        "college": "G.V.& A.D.S.L. College of Education (Id: C-32678)",
        "college_type": "Affiliated College",
        "state": "Andhra Pradesh",
        "district": "Prakasam"
    },
    {
        "university": "Acharya Nagarjuna University, Guntur (Id: U-0003)",
        "college": "G.V.R & S College of Education (Id: C-39228)",
        "college_type": "Affiliated College",
        "state": "Andhra Pradesh",
        "district": "Guntur"
    },
    {
        "university": "Acharya Nagarjuna University, Guntur (Id: U-0003)",
        "college": "G V R & S Degree College for Women (Id: C-32690)",
        "college_type": "Affiliated College",
        "state": "Andhra Pradesh",
        "district": "Guntur"
    },
    {
        "university": "Acharya Nagarjuna University, Guntur (Id: U-0003)",
        "college": "G.V.R.S Institute for Professional Studies (Id: C-32718)",
        "college_type": "Affiliated College",
        "state": "Andhra Pradesh",
        "district": "Guntur"
    },
    {
        "university": "Acharya Nagarjuna University, Guntur (Id: U-0003)",
        "college": "G.V.S.M. GOVT. Degree College (Id: C-32724)",
        "college_type": "Affiliated College",
        "state": "Andhra Pradesh",
        "district": "Prakasam"
    },
    {
        "university": "Acharya Nagarjuna University, Guntur (Id: U-0003)",
        "college": "Hazarath Ameeruddin College of Education (Id: C-39272)",
        "college_type": "Affiliated College",
        "state": "Andhra Pradesh",
        "district": "Prakasam"
    },
    {
        "university": "Acharya Nagarjuna University, Guntur (Id: U-0003)",
        "college": "Hindu College, Guntur (Id: C-32675)",
        "college_type": "Affiliated College",
        "state": "Andhra Pradesh",
        "district": "Guntur"
    },
    {
        "university": "Acharya Nagarjuna University, Guntur (Id: U-0003)",
        "college": "Hindu College of Education (Id: C-37107)",
        "college_type": "Affiliated College",
        "state": "Andhra Pradesh",
        "district": "Guntur"
    },
    {
        "university": "Acharya Nagarjuna University, Guntur (Id: U-0003)",
        "college": "Hindu College of Management, Guntur (Id: C-39487)",
        "college_type": "Affiliated College",
        "state": "Andhra Pradesh",
        "district": "Guntur"
    },
    {
        "university": "Acharya Nagarjuna University, Guntur (Id: U-0003)",
        "college": "Hindu College of Pharmacy (Id: C-32798)",
        "college_type": "Affiliated College",
        "state": "Andhra Pradesh",
        "district": "Guntur"
    },
    {
        "university": "Acharya Nagarjuna University, Guntur (Id: U-0003)",
        "college": "H.M.K.S. & M.G.S. Memorial College of Education (Id: C-32809)",
        "college_type": "Affiliated College",
        "state": "Andhra Pradesh",
        "district": "Guntur"
    },
    {
        "university": "Acharya Nagarjuna University, Guntur (Id: U-0003)",
        "college": "Ideal & S.K.C.M Degree College (Id: C-32830)",
        "college_type": "Affiliated College",
        "state": "Andhra Pradesh",
        "district": "Prakasam"
    },
    {
        "university": "Acharya Nagarjuna University, Guntur (Id: U-0003)",
        "college": "Indira Priyadarsni Law College (Id: C-32736)",
        "college_type": "Affiliated College",
        "state": "Andhra Pradesh",
        "district": "Prakasam"
    },
    {
        "university": "Acharya Nagarjuna University, Guntur (Id: U-0003)",
        "college": "J.C. College of Law (Id: C-32815)",
        "college_type": "Affiliated College",
        "state": "Andhra Pradesh",
        "district": "Guntur"
    },
    {
        "university": "Acharya Nagarjuna University, Guntur (Id: U-0003)",
        "college": "J.K.C. College (Id: C-32701)",
        "college_type": "Affiliated College",
        "state": "Andhra Pradesh",
        "district": "Guntur"
    },
    {
        "university": "Acharya Nagarjuna University, Guntur (Id: U-0003)",
        "college": "J.M.J. College for Women (Id: C-32812)",
        "college_type": "Affiliated College",
        "state": "Andhra Pradesh",
        "district": "Guntur"
    },
    {
        "university": "Acharya Nagarjuna University, Guntur (Id: U-0003)",
        "college": "J.R.R Navodaya Degree College (Id: C-39268)",
        "college_type": "Affiliated College",
        "state": "Andhra Pradesh",
        "district": "Guntur"
    },
    {
        "university": "Acharya Nagarjuna University, Guntur (Id: U-0003)",
        "college": "Kalikamba College of Education (Id: C-32722)",
        "college_type": "Affiliated College",
        "state": "Andhra Pradesh",
        "district": "Prakasam"
    },
    {
        "university": "Acharya Nagarjuna University, Guntur (Id: U-0003)",
        "college": "Kalyani MCA College, Eethamukkala (Id: C-42704)",
        "college_type": "Affiliated College",
        "state": "Andhra Pradesh",
        "district": "Prakasam"
    },
    {
        "university": "Acharya Nagarjuna University, Guntur (Id: U-0003)",
        "college": "Kamala College of Education (Id: C-39274)",
        "college_type": "Affiliated College",
        "state": "Andhra Pradesh",
        "district": "Prakasam"
    },
    {
        "university": "Acharya Nagarjuna University, Guntur (Id: U-0003)",
        "college": "Kamala Institute of Management Studies (Id: C-44107)",
        "college_type": "Affiliated College",
        "state": "Andhra Pradesh",
        "district": "Prakasam"
    },
    {
        "university": "Acharya Nagarjuna University, Guntur (Id: U-0003)",
        "college": "Kasturibai College of Education (Id: C-37209)",
        "college_type": "Affiliated College",
        "state": "Andhra Pradesh",
        "district": "Guntur"
    },
    {
        "university": "Acharya Nagarjuna University, Guntur (Id: U-0003)",
        "college": "K Chandrakala College (P.G.) (Id: C-32666)",
        "college_type": "Affiliated College",
        "state": "Andhra Pradesh",
        "district": "Guntur"
    },
    {
        "university": "Acharya Nagarjuna University, Guntur (Id: U-0003)",
        "college": "K.C Reddy Institute of Pharmaceutical Sciences (Id: C-39485)",
        "college_type": "Affiliated College",
        "state": "Andhra Pradesh",
        "district": "Guntur"
    },
    {
        "university": "Acharya Nagarjuna University, Guntur (Id: U-0003)",
        "college": "KC Reddy PG College, Janamguntapalem (Id: C-42658)",
        "college_type": "Affiliated College",
        "state": "Andhra Pradesh",
        "district": "Guntur"
    },
    {
        "university": "Acharya Nagarjuna University, Guntur (Id: U-0003)",
        "college": "K.L.N. Sanskrit College (Id: C-32794)",
        "college_type": "Affiliated College",
        "state": "Andhra Pradesh",
        "district": "Guntur"
    },
    {
        "university": "Acharya Nagarjuna University, Guntur (Id: U-0003)",
        "college": "K.L.R. Degree College (Id: C-32764)",
        "college_type": "Affiliated College",
        "state": "Andhra Pradesh",
        "district": "Prakasam"
    },
    {
        "university": "Acharya Nagarjuna University, Guntur (Id: U-0003)",
        "college": "Konijeti Rosaiah Siva Lakshmi College (Id: C-41017)",
        "college_type": "Affiliated College",
        "state": "Andhra Pradesh",
        "district": "Guntur"
    },
    {
        "university": "Acharya Nagarjuna University, Guntur (Id: U-0003)",
        "college": "Krishnaveni Degree College (Id: C-32694)",
        "college_type": "Affiliated College",
        "state": "Andhra Pradesh",
        "district": "Guntur"
    },
    {
        "university": "Acharya Nagarjuna University, Guntur (Id: U-0003)",
        "college": "Krishnaveni Degree College, Vinukonda (Id: C-42745)",
        "college_type": "Affiliated College",
        "state": "Andhra Pradesh",
        "district": "Guntur"
    },
    {
        "university": "Acharya Nagarjuna University, Guntur (Id: U-0003)",
        "college": "K R K Govt. Degree College (Id: C-32818)",
        "college_type": "Affiliated College",
        "state": "Andhra Pradesh",
        "district": "Prakasam"
    },
    {
        "university": "Acharya Nagarjuna University, Guntur (Id: U-0003)",
        "college": "K.S.R & K.R.K College of Education (Id: C-39235)",
        "college_type": "Affiliated College",
        "state": "Andhra Pradesh",
        "district": "Guntur"
    },
    {
        "university": "Acharya Nagarjuna University, Guntur (Id: U-0003)",
        "college": "K.S.R.N. Degree College, Govada (Id: C-39316)",
        "college_type": "Affiliated College",
        "state": "Andhra Pradesh",
        "district": "Guntur"
    },
    {
        "university": "Acharya Nagarjuna University, Guntur (Id: U-0003)",
        "college": "K.V.R., K.VR. & M.K.R College (Id: C-39270)",
        "college_type": "Affiliated College",
        "state": "Andhra Pradesh",
        "district": "Guntur"
    },
    {
        "university": "Acharya Nagarjuna University, Guntur (Id: U-0003)",
        "college": "Lakshmi Narsimha College of Education (Id: C-37212)",
        "college_type": "Affiliated College",
        "state": "Andhra Pradesh",
        "district": "Guntur"
    },
    {
        "university": "Acharya Nagarjuna University, Guntur (Id: U-0003)",
        "college": "Magunta Subba Rami Reddy Degree College (Id: C-32688)",
        "college_type": "Affiliated College",
        "state": "Andhra Pradesh",
        "district": "Prakasam"
    },
    {
        "university": "Acharya Nagarjuna University, Guntur (Id: U-0003)",
        "college": "Mahatma Gandhi College (Id: C-32829)",
        "college_type": "Affiliated College",
        "state": "Andhra Pradesh",
        "district": "Guntur"
    },
    {
        "university": "Acharya Nagarjuna University, Guntur (Id: U-0003)",
        "college": "Malineni Lakshmaiah B.Ed College (Id: C-39262)",
        "college_type": "Affiliated College",
        "state": "Andhra Pradesh",
        "district": "Prakasam"
    },
    {
        "university": "Acharya Nagarjuna University, Guntur (Id: U-0003)",
        "college": "M.A.M College of Education (Id: C-39245)",
        "college_type": "Affiliated College",
        "state": "Andhra Pradesh",
        "district": "Guntur"
    },
    {
        "university": "Acharya Nagarjuna University, Guntur (Id: U-0003)",
        "college": "M.A.M College of Pharmacy, Narsaraopet (Id: C-39470)",
        "college_type": "Affiliated College",
        "state": "Andhra Pradesh",
        "district": "Guntur"
    },
    {
        "university": "Acharya Nagarjuna University, Guntur (Id: U-0003)",
        "college": "Matrusri Oriental College (Id: C-32821)",
        "college_type": "Affiliated College",
        "state": "Andhra Pradesh",
        "district": "Guntur"
    },
    {
        "university": "Acharya Nagarjuna University, Guntur (Id: U-0003)",
        "college": "M.G College of Education (Id: C-37222)",
        "college_type": "Affiliated College",
        "state": "Andhra Pradesh",
        "district": "Prakasam"
    },
    {
        "university": "Acharya Nagarjuna University, Guntur (Id: U-0003)",
        "college": "Mittapalli Lakshmaiah & Sons Degree College, Piduguralla (Id: C-41008)",
        "college_type": "Affiliated College",
        "state": "Andhra Pradesh",
        "district": "Guntur"
    },
    {
        "university": "Acharya Nagarjuna University, Guntur (Id: U-0003)",
        "college": "M.L. College of MBA (Id: C-32751)",
        "college_type": "Affiliated College",
        "state": "Andhra Pradesh",
        "district": "Prakasam"
    },
    {
        "university": "Acharya Nagarjuna University, Guntur (Id: U-0003)",
        "college": "M.L. College of Pharmacy (Id: C-32658)",
        "college_type": "Affiliated College",
        "state": "Andhra Pradesh",
        "district": "Prakasam"
    },
    {
        "university": "Acharya Nagarjuna University, Guntur (Id: U-0003)",
        "college": "M.M.R Degree College, Macherla (Id: C-39305)",
        "college_type": "Affiliated College",
        "state": "Andhra Pradesh",
        "district": "Guntur"
    },
    {
        "university": "Acharya Nagarjuna University, Guntur (Id: U-0003)",
        "college": "Modern Degree College (Id: C-32674)",
        "college_type": "Affiliated College",
        "state": "Andhra Pradesh",
        "district": "Guntur"
    },
    {
        "university": "Acharya Nagarjuna University, Guntur (Id: U-0003)",
        "college": "Morning Star College (Id: C-32633)",
        "college_type": "Affiliated College",
        "state": "Andhra Pradesh",
        "district": "Guntur"
    },
    {
        "university": "Acharya Nagarjuna University, Guntur (Id: U-0003)",
        "college": "Mother Theresa Womens Degree College, Karampudi (Id: C-42779)",
        "college_type": "Affiliated College",
        "state": "Andhra Pradesh",
        "district": "Guntur"
    },
    {
        "university": "Acharya Nagarjuna University, Guntur (Id: U-0003)",
        "college": "M.S.R. Degree College, Bapatla (Id: C-39315)",
        "college_type": "Affiliated College",
        "state": "Andhra Pradesh",
        "district": "Guntur"
    },
    {
        "university": "Acharya Nagarjuna University, Guntur (Id: U-0003)",
        "college": "M.V.G.R. Degree College (Id: C-32719)",
        "college_type": "Affiliated College",
        "state": "Andhra Pradesh",
        "district": "Guntur"
    },
    {
        "university": "Acharya Nagarjuna University, Guntur (Id: U-0003)",
        "college": "M.V.R Degree College, Karlapalem (Id: C-39264)",
        "college_type": "Affiliated College",
        "state": "Andhra Pradesh",
        "district": "Guntur"
    },
    {
        "university": "Acharya Nagarjuna University, Guntur (Id: U-0003)",
        "college": "M.V.R.S. Viveka Degree College (Id: C-32721)",
        "college_type": "Affiliated College",
        "state": "Andhra Pradesh",
        "district": "Guntur"
    },
    {
        "university": "Acharya Nagarjuna University, Guntur (Id: U-0003)",
        "college": "Nagarjuna College of Education (Id: C-32641)",
        "college_type": "Affiliated College",
        "state": "Andhra Pradesh",
        "district": "Guntur"
    },
    {
        "university": "Acharya Nagarjuna University, Guntur (Id: U-0003)",
        "college": "Nagarjuna Institute of Management Studies, Chekurapadu (Id: C-39467)",
        "college_type": "Affiliated College",
        "state": "Andhra Pradesh",
        "district": "Prakasam"
    },
    {
        "university": "Acharya Nagarjuna University, Guntur (Id: U-0003)",
        "college": "Nalanda College of Education (Id: C-37207)",
        "college_type": "Affiliated College",
        "state": "Andhra Pradesh",
        "district": "Guntur"
    },
    {
        "university": "Acharya Nagarjuna University, Guntur (Id: U-0003)",
        "college": "National Minority Degree College (Id: C-32683)",
        "college_type": "Affiliated College",
        "state": "Andhra Pradesh",
        "district": "Prakasam"
    },
    {
        "university": "Acharya Nagarjuna University, Guntur (Id: U-0003)",
        "college": "Navya Chaitanya College of Education (Id: C-32758)",
        "college_type": "Affiliated College",
        "state": "Andhra Pradesh",
        "district": "Prakasam"
    },
    {
        "university": "Acharya Nagarjuna University, Guntur (Id: U-0003)",
        "college": "N.B.T & N V C College (Id: C-32746)",
        "college_type": "Affiliated College",
        "state": "Andhra Pradesh",
        "district": "Guntur"
    },
    {
        "university": "Acharya Nagarjuna University, Guntur (Id: U-0003)",
        "college": "New Era College of Education (Id: C-37106)",
        "college_type": "Affiliated College",
        "state": "Andhra Pradesh",
        "district": "Guntur"
    },
    {
        "university": "Acharya Nagarjuna University, Guntur (Id: U-0003)",
        "college": "Nirmala College of Pharmacy, Mangalagiri (Id: C-39481)",
        "college_type": "Affiliated College",
        "state": "Andhra Pradesh",
        "district": "Guntur"
    },
    {
        "university": "Acharya Nagarjuna University, Guntur (Id: U-0003)",
        "college": "N.N.R. & C.L. Degree College (Id: C-32743)",
        "college_type": "Affiliated College",
        "state": "Andhra Pradesh",
        "district": "Prakasam"
    },
    {
        "university": "Acharya Nagarjuna University, Guntur (Id: U-0003)",
        "college": "N.N.S. Vidya College of P.G. Studies (Id: C-32761)",
        "college_type": "Affiliated College",
        "state": "Andhra Pradesh",
        "district": "Prakasam"
    },
    {
        "university": "Acharya Nagarjuna University, Guntur (Id: U-0003)",
        "college": "N.N.S Vidya Degree College (Id: C-42657)",
        "college_type": "Affiliated College",
        "state": "Andhra Pradesh",
        "district": "Prakasam"
    },
    {
        "university": "Acharya Nagarjuna University, Guntur (Id: U-0003)",
        "college": "N.R.K & K.S.R Gupta College of Pharmacy (Id: C-39469)",
        "college_type": "Affiliated College",
        "state": "Andhra Pradesh",
        "district": "Guntur"
    },
    {
        "university": "Acharya Nagarjuna University, Guntur (Id: U-0003)",
        "college": "N.R.K. & K.S.R. Gupta Degree College (Id: C-32747)",
        "college_type": "Affiliated College",
        "state": "Andhra Pradesh",
        "district": "Guntur"
    },
    {
        "university": "Acharya Nagarjuna University, Guntur (Id: U-0003)",
        "college": "N.T.R Memorial Degree College (Id: C-32645)",
        "college_type": "Affiliated College",
        "state": "Andhra Pradesh",
        "district": "Prakasam"
    },
    {
        "university": "Acharya Nagarjuna University, Guntur (Id: U-0003)",
        "college": "Omega College of Education (Id: C-32682)",
        "college_type": "Affiliated College",
        "state": "Andhra Pradesh",
        "district": "Prakasam"
    },
    {
        "university": "Acharya Nagarjuna University, Guntur (Id: U-0003)",
        "college": "Palnadu College of Education, Narayanapuram (Id: C-39458)",
        "college_type": "Affiliated College",
        "state": "Andhra Pradesh",
        "district": "Guntur"
    },
    {
        "university": "Acharya Nagarjuna University, Guntur (Id: U-0003)",
        "college": "P.B.N. College (Id: C-32757)",
        "college_type": "Affiliated College",
        "state": "Andhra Pradesh",
        "district": "Guntur"
    },
    {
        "university": "Acharya Nagarjuna University, Guntur (Id: U-0003)",
        "college": "Pedanandipadu College of Arts and Sciences (Id: C-32781)",
        "college_type": "Affiliated College",
        "state": "Andhra Pradesh",
        "district": "Guntur"
    },
    {
        "university": "Acharya Nagarjuna University, Guntur (Id: U-0003)",
        "college": "P.N.C.A Degree College (Id: C-32620)",
        "college_type": "Affiliated College",
        "state": "Andhra Pradesh",
        "district": "Prakasam"
    },
    {
        "university": "Acharya Nagarjuna University, Guntur (Id: U-0003)",
        "college": "P.N.C & K.R. College (Id: C-32816)",
        "college_type": "Affiliated College",
        "state": "Andhra Pradesh",
        "district": "Guntur"
    },
    {
        "university": "Acharya Nagarjuna University, Guntur (Id: U-0003)",
        "college": "Prabhala Lakshminarayana Memorial Degree College (Id: C-32673)",
        "college_type": "Affiliated College",
        "state": "Andhra Pradesh",
        "district": "Guntur"
    },
    {
        "university": "Acharya Nagarjuna University, Guntur (Id: U-0003)",
        "college": "Prabhala PG College for Women, Nagarjuna Nagar (Id: C-39451)",
        "college_type": "Affiliated College",
        "state": "Andhra Pradesh",
        "district": "Guntur"
    },
    {
        "university": "Acharya Nagarjuna University, Guntur (Id: U-0003)",
        "college": "Pratap College of Education (Id: C-41026)",
        "college_type": "Affiliated College",
        "state": "Andhra Pradesh",
        "district": "Prakasam"
    },
    {
        "university": "Acharya Nagarjuna University, Guntur (Id: U-0003)",
        "college": "Prathiba Degree College (Id: C-32775)",
        "college_type": "Affiliated College",
        "state": "Andhra Pradesh",
        "district": "Prakasam"
    },
    {
        "university": "Acharya Nagarjuna University, Guntur (Id: U-0003)",
        "college": "Pratibha Degree College, Pedanandipadu (Id: C-41021)",
        "college_type": "Affiliated College",
        "state": "Andhra Pradesh",
        "district": "Guntur"
    },
    {
        "university": "Acharya Nagarjuna University, Guntur (Id: U-0003)",
        "college": "Priya Darisini Degree College (Id: C-32665)",
        "college_type": "Affiliated College",
        "state": "Andhra Pradesh",
        "district": "Guntur"
    },
    {
        "university": "Acharya Nagarjuna University, Guntur (Id: U-0003)",
        "college": "Priyadarsini Institute of Pharmaceutical Science (Id: C-39474)",
        "college_type": "Affiliated College",
        "state": "Andhra Pradesh",
        "district": "Guntur"
    },
    {
        "university": "Acharya Nagarjuna University, Guntur (Id: U-0003)",
        "college": "Priyanka College of Education (Id: C-32713)",
        "college_type": "Affiliated College",
        "state": "Andhra Pradesh",
        "district": "Prakasam"
    },
    {
        "university": "Acharya Nagarjuna University, Guntur (Id: U-0003)",
        "college": "P.S.B. College of Education (Id: C-39266)",
        "college_type": "Affiliated College",
        "state": "Andhra Pradesh",
        "district": "Prakasam"
    },
    {
        "university": "Acharya Nagarjuna University, Guntur (Id: U-0003)",
        "college": "Qis College of Education (Id: C-39276)",
        "college_type": "Affiliated College",
        "state": "Andhra Pradesh",
        "district": "Prakasam"
    },
    {
        "university": "Acharya Nagarjuna University, Guntur (Id: U-0003)",
        "college": "Radha Degree College, Vinukonda (Id: C-39304)",
        "college_type": "Affiliated College",
        "state": "Andhra Pradesh",
        "district": "Guntur"
    },
    {
        "university": "Acharya Nagarjuna University, Guntur (Id: U-0003)",
        "college": "Raghava Degree College - Ongole (Id: C-32642)",
        "college_type": "Affiliated College",
        "state": "Andhra Pradesh",
        "district": "Prakasam"
    },
    {
        "university": "Acharya Nagarjuna University, Guntur (Id: U-0003)",
        "college": "Rahul Institute of Pharmaceutical Sciences & Research (Id: C-41031)",
        "college_type": "Affiliated College",
        "state": "Andhra Pradesh",
        "district": "Prakasam"
    },
    {
        "university": "Acharya Nagarjuna University, Guntur (Id: U-0003)",
        "college": "Rahul Subramanyam Memorial Instt of Management Studies, Chirala (Id: C-41030)",
        "college_type": "Affiliated College",
        "state": "Andhra Pradesh",
        "district": "Prakasam"
    },
    {
        "university": "Acharya Nagarjuna University, Guntur (Id: U-0003)",
        "college": "Ravindra Bharathi College of Education (Id: C-32745)",
        "college_type": "Affiliated College",
        "state": "Andhra Pradesh",
        "district": "Prakasam"
    },
    {
        "university": "Acharya Nagarjuna University, Guntur (Id: U-0003)",
        "college": "Repalle Christian College (Id: C-32806)",
        "college_type": "Affiliated College",
        "state": "Andhra Pradesh",
        "district": "Guntur"
    },
    {
        "university": "Acharya Nagarjuna University, Guntur (Id: U-0003)",
        "college": "Repalle Christian College of Education (Id: C-32716)",
        "college_type": "Affiliated College",
        "state": "Andhra Pradesh",
        "district": "Guntur"
    },
    {
        "university": "Acharya Nagarjuna University, Guntur (Id: U-0003)",
        "college": "R.V.R. & J.C. College of Engineering (Id: C-32672)",
        "college_type": "Affiliated College",
        "state": "Andhra Pradesh",
        "district": "Guntur"
    },
    {
        "university": "Acharya Nagarjuna University, Guntur (Id: U-0003)",
        "college": "R.V.R.R. College of Education (Id: C-32725)",
        "college_type": "Affiliated College",
        "state": "Andhra Pradesh",
        "district": "Guntur"
    },
    {
        "university": "Acharya Nagarjuna University, Guntur (Id: U-0003)",
        "college": "R.V.V.N. College (Id: C-32687)",
        "college_type": "Affiliated College",
        "state": "Andhra Pradesh",
        "district": "Guntur"
    },
    {
        "university": "Acharya Nagarjuna University, Guntur (Id: U-0003)",
        "college": "S.A.B.R. Govt. Degree College (Id: C-32765)",
        "college_type": "Affiliated College",
        "state": "Andhra Pradesh",
        "district": "Guntur"
    },
    {
        "university": "Acharya Nagarjuna University, Guntur (Id: U-0003)",
        "college": "Sadhana Degree College (Id: C-32755)",
        "college_type": "Affiliated College",
        "state": "Andhra Pradesh",
        "district": "Guntur"
    },
    {
        "university": "Acharya Nagarjuna University, Guntur (Id: U-0003)",
        "college": "Sadineni Chowdaraiah College of Arts & Science (Id: C-32739)",
        "college_type": "Affiliated College",
        "state": "Andhra Pradesh",
        "district": "Guntur"
    },
    {
        "university": "Acharya Nagarjuna University, Guntur (Id: U-0003)",
        "college": "Sai Chaitanya Degree College Giddalur (Id: C-39303)",
        "college_type": "Affiliated College",
        "state": "Andhra Pradesh",
        "district": "Prakasam"
    },
    {
        "university": "Acharya Nagarjuna University, Guntur (Id: U-0003)",
        "college": "Sarada College of Pharmaceutical Sciences (Id: C-39479)",
        "college_type": "Affiliated College",
        "state": "Andhra Pradesh",
        "district": "Guntur"
    },
    {
        "university": "Acharya Nagarjuna University, Guntur (Id: U-0003)",
        "college": "Sarada Degree College, Medarametla (Id: C-44488)",
        "college_type": "Affiliated College",
        "state": "Andhra Pradesh",
        "district": "Prakasam"
    },
    {
        "university": "Acharya Nagarjuna University, Guntur (Id: U-0003)",
        "college": "Saraswathi College of Arts & Science, Dachepalli (Id: C-41013)",
        "college_type": "Affiliated College",
        "state": "Andhra Pradesh",
        "district": "Guntur"
    },
    {
        "university": "Acharya Nagarjuna University, Guntur (Id: U-0003)",
        "college": "S.B.G. Degree College, Sattenapalli (Id: C-40606)",
        "college_type": "Affiliated College",
        "state": "Andhra Pradesh",
        "district": "Guntur"
    },
    {
        "university": "Acharya Nagarjuna University, Guntur (Id: U-0003)",
        "college": "S.B.M.S. Degree College (Id: C-32646)",
        "college_type": "Affiliated College",
        "state": "Andhra Pradesh",
        "district": "Guntur"
    },
    {
        "university": "Acharya Nagarjuna University, Guntur (Id: U-0003)",
        "college": "S.B.Swamy Sanskrit College (Id: C-32728)",
        "college_type": "Affiliated College",
        "state": "Andhra Pradesh",
        "district": "Guntur"
    },
    {
        "university": "Acharya Nagarjuna University, Guntur (Id: U-0003)",
        "college": "S.B.V.S.R College of Education, Cheemakurthi (Id: C-42742)",
        "college_type": "Affiliated College",
        "state": "Andhra Pradesh",
        "district": "Prakasam"
    },
    {
        "university": "Acharya Nagarjuna University, Guntur (Id: U-0003)",
        "college": "Seven Hills College of Education (Id: C-37208)",
        "college_type": "Affiliated College",
        "state": "Andhra Pradesh",
        "district": "Guntur"
    },
    {
        "university": "Acharya Nagarjuna University, Guntur (Id: U-0003)",
        "college": "S.G.H.R. & M.C.M.R.College (Id: C-32730)",
        "college_type": "Affiliated College",
        "state": "Andhra Pradesh",
        "district": "Guntur"
    },
    {
        "university": "Acharya Nagarjuna University, Guntur (Id: U-0003)",
        "college": "S.G.K Govt. Degree College, Vinukonda (Id: C-42245)",
        "college_type": "Affiliated College",
        "state": "Andhra Pradesh",
        "district": "Guntur"
    },
    {
        "university": "Acharya Nagarjuna University, Guntur (Id: U-0003)",
        "college": "S.G.K. Oriental College (Id: C-32697)",
        "college_type": "Affiliated College",
        "state": "Andhra Pradesh",
        "district": "Guntur"
    },
    {
        "university": "Acharya Nagarjuna University, Guntur (Id: U-0003)",
        "college": "S.G.T. & J.V.B.College (Id: C-32635)",
        "college_type": "Affiliated College",
        "state": "Andhra Pradesh",
        "district": "Guntur"
    },
    {
        "university": "Acharya Nagarjuna University, Guntur (Id: U-0003)",
        "college": "S.G.V. Oriental College (Id: C-32783)",
        "college_type": "Affiliated College",
        "state": "Andhra Pradesh",
        "district": "Prakasam"
    },
    {
        "university": "Acharya Nagarjuna University, Guntur (Id: U-0003)",
        "college": "Shams-Ul_Uloom College of Education, Markapur (Id: C-39301)",
        "college_type": "Affiliated College",
        "state": "Andhra Pradesh",
        "district": "Prakasam"
    },
    {
        "university": "Acharya Nagarjuna University, Guntur (Id: U-0003)",
        "college": "Shams-Ul-Uloom College of Education, Podili (Id: C-39477)",
        "college_type": "Affiliated College",
        "state": "Andhra Pradesh",
        "district": "Prakasam"
    },
    {
        "university": "Acharya Nagarjuna University, Guntur (Id: U-0003)",
        "college": "Shivani Degree College (Id: C-36921)",
        "college_type": "Affiliated College",
        "state": "Andhra Pradesh",
        "district": "Guntur"
    },
    {
        "university": "Acharya Nagarjuna University, Guntur (Id: U-0003)",
        "college": "Siddhartha Institute of Pharmaceutical Sciences, Jonnalagadda (Id: C-39454)",
        "college_type": "Affiliated College",
        "state": "Andhra Pradesh",
        "district": "Guntur"
    },
    {
        "university": "Acharya Nagarjuna University, Guntur (Id: U-0003)",
        "college": "SIMS College of Education (Id: C-37210)",
        "college_type": "Affiliated College",
        "state": "Andhra Pradesh",
        "district": "Guntur"
    },
    {
        "university": "Acharya Nagarjuna University, Guntur (Id: U-0003)",
        "college": "SIMS College of Life Sciences, Guntur (Id: C-41033)",
        "college_type": "Affiliated College",
        "state": "Andhra Pradesh",
        "district": "Guntur"
    },
    {
        "university": "Acharya Nagarjuna University, Guntur (Id: U-0003)",
        "college": "SIMS College of Pharmacy (Id: C-32788)",
        "college_type": "Affiliated College",
        "state": "Andhra Pradesh",
        "district": "Guntur"
    },
    {
        "university": "Acharya Nagarjuna University, Guntur (Id: U-0003)",
        "college": "S.K.B.R. Govt. College (Id: C-32691)",
        "college_type": "Affiliated College",
        "state": "Andhra Pradesh",
        "district": "Guntur"
    },
    {
        "university": "Acharya Nagarjuna University, Guntur (Id: U-0003)",
        "college": "S.K.R.B.R. College (Id: C-32738)",
        "college_type": "Affiliated College",
        "state": "Andhra Pradesh",
        "district": "Guntur"
    },
    {
        "university": "Acharya Nagarjuna University, Guntur (Id: U-0003)",
        "college": "S.K.S.V. Degree College for Women (Id: C-32661)",
        "college_type": "Affiliated College",
        "state": "Andhra Pradesh",
        "district": "Guntur"
    },
    {
        "university": "Acharya Nagarjuna University, Guntur (Id: U-0003)",
        "college": "S.L.V. College of Education (Id: C-42244)",
        "college_type": "Affiliated College",
        "state": "Andhra Pradesh",
        "district": "Prakasam"
    },
    {
        "university": "Acharya Nagarjuna University, Guntur (Id: U-0003)",
        "college": "S.M.P.A. Degree College (Id: C-32814)",
        "college_type": "Affiliated College",
        "state": "Andhra Pradesh",
        "district": "Guntur"
    },
    {
        "university": "Acharya Nagarjuna University, Guntur (Id: U-0003)",
        "college": "SMS & SMCMR College of Education (Id: C-37217)",
        "college_type": "Affiliated College",
        "state": "Andhra Pradesh",
        "district": "Guntur"
    },
    {
        "university": "Acharya Nagarjuna University, Guntur (Id: U-0003)",
        "college": "Smt. Koonapareddy Prameela Rani Degree College, Parchoor (Id: C-39312)",
        "college_type": "Affiliated College",
        "state": "Andhra Pradesh",
        "district": "Prakasam"
    },
    {
        "university": "Acharya Nagarjuna University, Guntur (Id: U-0003)",
        "college": "Smt. Sanagala Prameela Degree College (Id: C-32685)",
        "college_type": "Affiliated College",
        "state": "Andhra Pradesh",
        "district": "Guntur"
    },
    {
        "university": "Acharya Nagarjuna University, Guntur (Id: U-0003)",
        "college": "S M Y College of Education (Id: C-32660)",
        "college_type": "Affiliated College",
        "state": "Andhra Pradesh",
        "district": "Prakasam"
    },
    {
        "university": "Acharya Nagarjuna University, Guntur (Id: U-0003)",
        "college": "S.N.B.T. Degree College for Women (Id: C-32737)",
        "college_type": "Affiliated College",
        "state": "Andhra Pradesh",
        "district": "Guntur"
    },
    {
        "university": "Acharya Nagarjuna University, Guntur (Id: U-0003)",
        "college": "S.N.B.T.M. College of Education (Id: C-32622)",
        "college_type": "Affiliated College",
        "state": "Andhra Pradesh",
        "district": "Guntur"
    },
    {
        "university": "Acharya Nagarjuna University, Guntur (Id: U-0003)",
        "college": "Sri Chaitanya College of Education (Id: C-39263)",
        "college_type": "Affiliated College",
        "state": "Andhra Pradesh",
        "district": "Prakasam"
    },
    {
        "university": "Acharya Nagarjuna University, Guntur (Id: U-0003)",
        "college": "Sri C.V. Raman College of Computer Science (Id: C-39463)",
        "college_type": "Affiliated College",
        "state": "Andhra Pradesh",
        "district": "Prakasam"
    },
    {
        "university": "Acharya Nagarjuna University, Guntur (Id: U-0003)",
        "college": "Sri Gayatri Vidya Parishad Degree College (Id: C-32715)",
        "college_type": "Affiliated College",
        "state": "Andhra Pradesh",
        "district": "Prakasam"
    },
    {
        "university": "Acharya Nagarjuna University, Guntur (Id: U-0003)",
        "college": "Sri Gowtham College of Education, Darsi (Id: C-39447)",
        "college_type": "Affiliated College",
        "state": "Andhra Pradesh",
        "district": "Prakasam"
    },
    {
        "university": "Acharya Nagarjuna University, Guntur (Id: U-0003)",
        "college": "Sri Gowtham Degree College, Kandulapuram (Id: C-41009)",
        "college_type": "Affiliated College",
        "state": "Andhra Pradesh",
        "district": "Prakasam"
    },
    {
        "university": "Acharya Nagarjuna University, Guntur (Id: U-0003)",
        "college": "Sri Gowthami Degree College, Darsi (Id: C-41011)",
        "college_type": "Affiliated College",
        "state": "Andhra Pradesh",
        "district": "Prakasam"
    },
    {
        "university": "Acharya Nagarjuna University, Guntur (Id: U-0003)",
        "college": "Sri Harsha's Womens Degree College, Cumbum (Id: C-44486)",
        "college_type": "Affiliated College",
        "state": "Andhra Pradesh",
        "district": "Prakasam"
    },
    {
        "university": "Acharya Nagarjuna University, Guntur (Id: U-0003)",
        "college": "Sri Harshini Degree College, Martur (Id: C-41024)",
        "college_type": "Affiliated College",
        "state": "Andhra Pradesh",
        "district": "Prakasam"
    },
    {
        "university": "Acharya Nagarjuna University, Guntur (Id: U-0003)",
        "college": "Sri Harshini Degree College, Ongole (Id: C-41023)",
        "college_type": "Affiliated College",
        "state": "Andhra Pradesh",
        "district": "Prakasam"
    },
    {
        "university": "Acharya Nagarjuna University, Guntur (Id: U-0003)",
        "college": "Sri Jeevana Jyothi Degree College, Giddalur (Id: C-41010)",
        "college_type": "Affiliated College",
        "state": "Andhra Pradesh",
        "district": "Prakasam"
    },
    {
        "university": "Acharya Nagarjuna University, Guntur (Id: U-0003)",
        "college": "Sriji Degree College (Id: C-32774)",
        "college_type": "Affiliated College",
        "state": "Andhra Pradesh",
        "district": "Prakasam"
    }
]